MANIFEST.in
setup.py
chainercmd/__init__.py
chainercmd/init.py
chainercmd/test.py
chainercmd/train.py
chainercmd.egg-info/PKG-INFO
chainercmd.egg-info/SOURCES.txt
chainercmd.egg-info/dependency_links.txt
chainercmd.egg-info/entry_points.txt
chainercmd.egg-info/not-zip-safe
chainercmd.egg-info/requires.txt
chainercmd.egg-info/top_level.txt
chainercmd/bin/__init__.py
chainercmd/bin/chainercmd.py
chainercmd/config/__init__.py
chainercmd/config/base.py
chainercmd/config/dataset.py
chainercmd/config/evaluator_creator.py
chainercmd/config/extension.py
chainercmd/config/model.py
chainercmd/config/optimizer.py
chainercmd/config/updater_creator.py
chainercmd/template/__init__.py
chainercmd/template/config.yml
chainercmd/template/custom_extension.py
chainercmd/template/dataset.py
chainercmd/template/evaluator_creator.py
chainercmd/template/loss.py
chainercmd/template/model.py
chainercmd/template/updater_creator.py