Metadata-Version: 1.2
Name: chainercmd
Version: 3.1.0a2
Summary: Command Line Tools for Chainer
Home-page: https://github.com/mitmul/chainercmd
Author: Shunta Saito
Author-email: shunta.saito@gmail.com
License: MIT
Keywords: chainer deeplearning
Platform: UNKNOWN
Requires-Python: >=3.6.2
